{
  "version": "7",
  "dialect": "postgresql",
  "entries": [
    {
      "idx": 0,
      "version": "7",
      "when": 1759242596252,
      "tag": "0000_silky_tenebrous",
      "breakpoints": true
    },
    {
      "idx": 1,
      "version": "7",
      "when": 1759242843586,
      "tag": "0001_purple_captain_stacy",
      "breakpoints": true
    },
    {
      "idx": 2,
      "version": "7",
      "when": 1759253518842,
      "tag": "0002_absurd_madame_hydra",
      "breakpoints": true
    },
    {
      "idx": 3,
      "version": "7",
      "when": 1759299392981,
      "tag": "0003_minor_speed",
      "breakpoints": true
    },
    {
      "idx": 4,
      "version": "7",
      "when": 1759302107383,
      "tag": "0004_cynical_silver_samurai",
      "breakpoints": true
    },
    {
      "idx": 5,
      "version": "7",
      "when": 1759324134685,
      "tag": "0005_orange_sunset_bain",
      "breakpoints": true
    },
    {
      "idx": 6,
      "version": "7",
      "when": 1759405242748,
      "tag": "0006_aspiring_prodigy",
      "breakpoints": true
    },
    {
      "idx": 7,
      "version": "7",
      "when": 1759578411927,
      "tag": "0007_giant_red_shift",
      "breakpoints": true
    },
    {
      "idx": 8,
      "version": "7",
      "when": 1759592559847,
      "tag": "0008_left_slyde",
      "breakpoints": true
    }
  ]
}